givemecolor/__init__.py
givemecolor/main.py
givemecolor-1.0.1.dist-info/METADATA
givemecolor-1.0.1.dist-info/WHEEL
givemecolor-1.0.1.dist-info/entry_points.txt
givemecolor-1.0.1.dist-info/top_level.txt
givemecolor-1.0.1.dist-info/RECORD
