Metadata-Version: 2.1
Name: givemecolor
Version: 1.0.1
Summary: Giveme Color is a random color generator package. Every time it returns a new random color and copies it to your clipboard.
Home-page: https://github.com/imparth7/giveme-color-py
Author: imparth
Project-URL: Bug Reports, https://github.com/imparth7/giveme-color-py/issues
Project-URL: Homepage, https://github.com/imparth7/giveme-color-py#readme
Keywords: random,color
Classifier: Programming Language :: Python :: 3
Classifier: License :: OSI Approved :: MIT License
Classifier: Operating System :: OS Independent
Requires-Python: >=3.6
